[{"dataBrand":[
				{"name":"九牧王","visit": 801 ,"id":0},
				{"name":"战地吉普","visit": 1699 ,"id":1},
				{"name":"南极人","visit":1412 ,"id":2},
				{"name":"比菲力","visit":415 ,"id":3},
				{"name":"丹顿公子","visit":593 ,"id":4},
				{"name":"杰森迪亚","visit":634 ,"id":5},
				{"name":"花花公子","visit":508 ,"id":6},
				{"name":"丹杰仕","visit":344 ,"id":7},
				{"name":"班尼路","visit":503 ,"id":8},
				{"name":"真维斯","visit":266 ,"id":9}
				],"dataCompare":[{
					"x" : 0 , "y" : 1 , "visit" : 88 
					},{
					"x" : 0 , "y" : 2 , "visit" : 99 
					},{
					"x" : 0 , "y" : 3 , "visit" : 22
					},{
					"x" : 0 , "y" : 4 , "visit" : 53 
					},{
					"x" : 0 , "y" : 5 , "visit" : 59 
					},{
					"x" : 0 , "y" : 6 , "visit" : 37 
					},{
					"x" : 0 , "y" : 7, "visit" : 20 
					},{
					"x" : 0 , "y" : 8 , "visit" : 28 
					},{
					"x" : 0 , "y" : 9 , "visit" : 7 
					},
					
					{
					"x" : 1 , "y" : 2 , "visit" : 221 
					},{
					"x" : 1 , "y" : 3 , "visit" : 75
					},{
					"x" : 1 , "y" : 4 , "visit" : 42 
					},{
					"x" : 1 , "y" : 5 , "visit" : 62 
					},{
					"x" : 1 , "y" : 6 , "visit" : 81 
					},{
					"x" : 1 , "y" : 7, "visit" : 36 
					},{
					"x" : 1 , "y" : 8 , "visit" : 44 
					},{
					"x" : 1 , "y" : 9 , "visit" : 15 
					},
					
					{
					"x" : 2 , "y" : 3 , "visit" : 56
					},{
					"x" : 2 , "y" : 4 , "visit" : 83 
					},{
					"x" : 2 , "y" : 5 , "visit" : 103 
					},{
					"x" : 2 , "y" : 6 , "visit" : 80 
					},{
					"x" : 2 , "y" : 7, "visit" : 35 
					},{
					"x" : 2 , "y" : 8 , "visit" : 43 
					},{
					"x" : 2 , "y" : 9 , "visit" : 16 
					},
					
					
					
					{
					"x" : 3 , "y" : 4 , "visit" : 14 
					},{
					"x" : 3 , "y" : 5 , "visit" : 17 
					},{
					"x" : 3 , "y" : 6 , "visit" : 35 
					},{
					"x" : 3 , "y" : 7, "visit" : 12 
					},{
					"x" : 3 , "y" : 8 , "visit" : 14 
					},{
					"x" : 3 , "y" : 9 , "visit" : 2 
					},
					
					
					
					{
					"x" : 4 , "y" : 5 , "visit" : 107 
					},{
					"x" : 4 , "y" : 6 , "visit" : 27
					},{
					"x" : 4 , "y" : 7, "visit" : 34 
					},{
					"x" : 4 , "y" : 8 , "visit" : 21 
					},{
					"x" : 4 , "y" : 9 , "visit" : 9
					},
					
					
					{
					"x" : 5 , "y" : 6 , "visit" : 29
					},{
					"x" : 5 , "y" : 7, "visit" : 25 
					},{
					"x" : 5 , "y" : 8 , "visit" : 27 
					},{
					"x" : 5 , "y" : 9 , "visit" : 5
					},
					
					{
					"x" : 6 , "y" : 7, "visit" : 22 
					},{
					"x" : 6 , "y" : 8 , "visit" : 20 
					},{
					"x" : 6 , "y" : 9 , "visit" : 8
					},
					
					
					{
					"x" :  7, "y" : 8 , "visit" : 14 
					},{
					"x" :  7, "y" : 9 , "visit" : 7
					},
					
					
					{
					"x" :  8, "y" : 9 , "visit" : 16
					}
				],
				"datatype": "休闲裤"},
				{"dataBrand":[
				{"name":"九牧王","visit": 501 ,"id":0},
				{"name":"红豆","visit": 266,"id":1},
				{"name":"杉杉","visit":297 ,"id":2},
				{"name":"花花公子","visit":203 ,"id":3},
				{"name":"威可多","visit":147 ,"id":4},
				{"name":"恒源祥","visit":186 ,"id":5},
				{"name":"传棨","visit":170 ,"id":6},
				{"name":"花花公子贵宾","visit":102 ,"id":7},
				{"name":"纱格","visit":120 ,"id":8},
				{"name":"领般","visit":124 ,"id":9}
				],"dataCompare":[{
					"x" : 0 , "y" : 1 , "visit" : 26 
					},{
					"x" : 0 , "y" : 2 , "visit" : 39 
					},{
					"x" : 0 , "y" : 3 , "visit" : 27
					},{
					"x" : 0 , "y" : 4 , "visit" : 21 
					},{
					"x" : 0 , "y" : 5 , "visit" : 36 
					},{
					"x" : 0 , "y" : 6 , "visit" : 20 
					},{
					"x" : 0 , "y" : 7, "visit" : 16
					},{
					"x" : 0 , "y" : 8 , "visit" : 16 
					},{
					"x" : 0 , "y" : 9 , "visit" : 17
					},
					
					{
					"x" : 1 , "y" : 2 , "visit" : 41 
					},{
					"x" : 1 , "y" : 3 , "visit" : 31
					},{
					"x" : 1 , "y" : 4 , "visit" : 11 
					},{
					"x" : 1 , "y" : 5 , "visit" : 15 
					},{
					"x" : 1 , "y" : 6 , "visit" : 13 
					},{
					"x" : 1 , "y" : 7, "visit" : 19
					},{
					"x" : 1 , "y" : 8 , "visit" : 10 
					},{
					"x" : 1 , "y" : 9 , "visit" : 19 
					},
					
					{
					"x" : 2 , "y" : 3 , "visit" : 34
					},{
					"x" : 2 , "y" : 4 , "visit" : 12 
					},{
					"x" : 2 , "y" : 5 , "visit" : 18 
					},{
					"x" : 2 , "y" : 6 , "visit" : 21 
					},{
					"x" : 2 , "y" : 7, "visit" : 16
					},{
					"x" : 2 , "y" : 8 , "visit" : 10 
					},{
					"x" : 2 , "y" : 9 , "visit" : 17 
					},
					
					
					
					{
					"x" : 3 , "y" : 4 , "visit" : 10 
					},{
					"x" : 3 , "y" : 5 , "visit" : 20 
					},{
					"x" : 3 , "y" : 6 , "visit" : 18 
					},{
					"x" : 3 , "y" : 7, "visit" : 26
					},{
					"x" : 3 , "y" : 8 , "visit" : 17 
					},{
					"x" : 3 , "y" : 9 , "visit" : 13
					},
					
					
					
					{
					"x" : 4 , "y" : 5 , "visit" : 8 
					},{
					"x" : 4 , "y" : 6 , "visit" : 6
					},{
					"x" : 4 , "y" : 7, "visit" : 6 
					},{
					"x" : 4 , "y" : 8 , "visit" : 8 
					},{
					"x" : 4 , "y" : 9 , "visit" : 10
					},
					
					
					{
					"x" : 5 , "y" : 6 , "visit" : 7
					},{
					"x" : 5 , "y" : 7, "visit" : 14 
					},{
					"x" : 5 , "y" : 8 , "visit" : 6 
					},{
					"x" : 5 , "y" : 9 , "visit" : 8
					},
					
					{
					"x" : 6 , "y" : 7, "visit" : 10 
					},{
					"x" : 6 , "y" : 8 , "visit" : 13 
					},{
					"x" : 6 , "y" : 9 , "visit" : 22
					},
					
					
					{
					"x" :  7, "y" : 8 , "visit" : 12 
					},{
					"x" :  7, "y" : 9 , "visit" : 11
					},
					
					
					{
					"x" :  8, "y" : 9 , "visit" : 13
					}
				],
				"datatype": "西裤"}
				
				
				]
